[
    {
        "id": "1",
        "name": "[압구정주꾸미] 주꾸미 볶음 2종 (택1)",
        "poster" : "https://res.cloudinary.com/dpr8m7xge/image/upload/v1716534058/product/product1.jpg",
        "before" : "7,800",
        "sales" : "15",
        "price" : "6,630",
        "review" : "1,434",
        "category" : "food"
    },
    {
        "id": "2",
        "name": "[4,900원 균일가] 인기 국/탕/찌개 12종 (택2)",
        "poster" : "https://res.cloudinary.com/dpr8m7xge/image/upload/v1716534058/product/product2.jpg",
        "before" : "7,800",
        "sales" : "15",
        "price" : "6,630",
        "review" : "1,434",
        "category" : "food"
    },
    {
        "id": "3",
        "name": "[KF365] 대추방울토마토 750g",
        "poster" : "https://res.cloudinary.com/dpr8m7xge/image/upload/v1716534058/product/product3.jpg",
        "before" : "7,800",
        "sales" : "15",
        "price" : "6,630",
        "review" : "1,434",
        "category" : "food"
    },
    {
        "id": "4",
        "name": "[올마레] 춘천 국물 닭갈비 떡볶이",
        "poster" : "https://res.cloudinary.com/dpr8m7xge/image/upload/v1716534058/product/product4.jpg",
        "before" : "7,800",
        "sales" : "15",
        "price" : "6,630",
        "review" : "1,434",
        "category" : "food"
    },
    {
        "id": "5",
        "name": "[사미헌] 갈비탕",
        "poster" : "https://res.cloudinary.com/dpr8m7xge/image/upload/v1716534058/product/product5.jpg",
        "before" : "7,800",
        "sales" : "15",
        "price" : "6,630",
        "review" : "1,434",
        "category" : "food"
    },
    {
        "id": "6",
        "name": "[KF365] 훈제오리 150g*2pk",
        "poster" : "https://res.cloudinary.com/dpr8m7xge/image/upload/v1716534058/product/product6.jpg",
        "before" : "7,800",
        "sales" : "15",
        "price" : "6,630",
        "review" : "1,434",
        "category" : "food"
    },
    {
        "id": "7",
        "name": "[하코야] 살얼음 동동 냉메밀 소바 2인분",
        "poster" : "https://res.cloudinary.com/dpr8m7xge/image/upload/v1716534058/product/product7.jpg",
        "before" : "7,800",
        "sales" : "15",
        "price" : "6,630",
        "review" : "1,434",
        "category" : "food"
    },
    {
        "id": "8",
        "name": "[남향푸드또띠아] 간편 브리또 15종 2개입 (택1)",
        "poster" : "https://res.cloudinary.com/dpr8m7xge/image/upload/v1716534058/product/product8.jpg",
        "before" : "7,800",
        "sales" : "15",
        "price" : "6,630",
        "review" : "1,434",
        "category" : "food"
    },
]